setup.py
gaussian_binomial_distributions1/Binomialdistribution.py
gaussian_binomial_distributions1/Gaussiandistribution.py
gaussian_binomial_distributions1/Generaldistribution.py
gaussian_binomial_distributions1/__init__.py
gaussian_binomial_distributions1.egg-info/PKG-INFO
gaussian_binomial_distributions1.egg-info/SOURCES.txt
gaussian_binomial_distributions1.egg-info/dependency_links.txt
gaussian_binomial_distributions1.egg-info/not-zip-safe
gaussian_binomial_distributions1.egg-info/top_level.txt