Metadata-Version: 1.0
Name: gaussian-binomial-distributions1
Version: 1.1
Summary: Gaussian distributions
Home-page: UNKNOWN
Author: Gollapinni Karthik
Author-email: UNKNOWN
License: UNKNOWN
Platform: UNKNOWN
